<?xml version="1.0" encoding="utf-8" ?><dwsync><file name="Arc1_Small_Bussiness_icons-01.png" server="ftp.benjaminferreiradesigns.com//public_html/" local="3454025304" remote="323953104369916664" Dst="-1" /><file name="Arc1_Small_Bussiness_icons-08.png" server="ftp.benjaminferreiradesigns.com//public_html/" local="3454025304" remote="323953104369916664" Dst="-1" /><file name="Arc1_Small_Bussiness_icons-10.png" server="ftp.benjaminferreiradesigns.com//public_html/" local="3454025305" remote="323953104369916664" Dst="-1" /><file name="Arc1_Small_Bussiness_icons-12.png" server="ftp.benjaminferreiradesigns.com//public_html/" local="3454025305" remote="323953104369916664" Dst="-1" /><file name="HTML5_1Color_White.png" server="ftp.benjaminferreiradesigns.com//public_html/" local="3454025306" remote="1662695437030300408" Dst="-1" /><file name="HTML5_3D_Effects_512.png" server="ftp.benjaminferreiradesigns.com//public_html/" local="3454025306" remote="323953104369916664" Dst="-1" /><file name="HTML5_Connectivity_512.png" server="ftp.benjaminferreiradesigns.com//public_html/" local="3454025306" remote="323953104369916664" Dst="-1" /><file name="HTML5_Device_Access_512.png" server="ftp.benjaminferreiradesigns.com//public_html/" local="3454025306" remote="323953104369916664" Dst="-1" /><file name="Arc1_Small_Bussiness_icons.ai" server="ftp.benjaminferreiradesigns.com//public_html/" local="3454025307" remote="323953104369916664" Dst="-1" /><file name="HTML5_Logo_512.png" server="ftp.benjaminferreiradesigns.com//public_html/" local="3454025307" remote="323953104369916664" Dst="-1" /><file name="HTML5_Multimedia_512.png" server="ftp.benjaminferreiradesigns.com//public_html/" local="3454025307" remote="323953104369916664" Dst="-1" /><file name="HTML5_Offline_Storage_512.png" server="ftp.benjaminferreiradesigns.com//public_html/" local="3454025307" remote="323953104369916664" Dst="-1" /><file name="HTML5_Performance_512.png" server="ftp.benjaminferreiradesigns.com//public_html/" local="3454025307" remote="1662695437030300408" Dst="-1" /><file name="HTML5_Semantics_512.png" server="ftp.benjaminferreiradesigns.com//public_html/" local="3454025307" remote="1662695437030300408" Dst="-1" /><file name="Thumb_Gallery10_Poster1.jpg" server="ftp.benjaminferreiradesigns.com//public_html/" local="3454025308" remote="323953104369916664" Dst="-1" /><file name="HTML5_Styling_512.png" server="ftp.benjaminferreiradesigns.com//public_html/" local="3454025307" remote="1662695437030300408" Dst="-1" /><file name="Thumb_Gallery10_Poster2.jpg" server="ftp.benjaminferreiradesigns.com//public_html/" local="3454025307" remote="323953104369916664" Dst="-1" /><file name="Thumb_Gallery10_Poster4.jpg" server="ftp.benjaminferreiradesigns.com//public_html/" local="3454025308" remote="323953104369916664" Dst="-1" /><file name="Thumb_Gallery10_Poster3.jpg" server="ftp.benjaminferreiradesigns.com//public_html/" local="3454025308" remote="323953104369916664" Dst="-1" /><file name="Thumb_Gallery10_Poster5.jpg" server="ftp.benjaminferreiradesigns.com//public_html/" local="3454025308" remote="323953104369916664" Dst="-1" /><file name="Thumb_Gallery10_Poster6.jpg" server="ftp.benjaminferreiradesigns.com//public_html/" local="3454025308" remote="323953104369916664" Dst="-1" /><file name="Thumb_Gallery10_Poster7.jpg" server="ftp.benjaminferreiradesigns.com//public_html/" local="3454025308" remote="323953104369916664" Dst="-1" /><file name="Thumb_Gallery10_poster1.jpg" server="ftp.benjaminferreiradesigns.com//public_html/" local="3454025308" remote="3208438567539481936" Dst="-1" /><file name="Thumb_Gallery10_poster4.jpg" server="ftp.benjaminferreiradesigns.com//public_html/" local="3454025308" remote="3189534595403652432" Dst="-1" /><file name="Thumb_Gallery10_poster5.jpg" server="ftp.benjaminferreiradesigns.com//public_html/" local="3454025308" remote="3189534595403652432" Dst="-1" /><file name="Thumb_Gallery10_poster6.jpg" server="ftp.benjaminferreiradesigns.com//public_html/" local="3454025308" remote="3209774542886706512" Dst="-1" /><file name="Thumb_Gallery1_Book1.jpg" server="ftp.benjaminferreiradesigns.com//public_html/" local="3454025309" remote="3219616340186405624" Dst="-1" /><file name="Thumb_Gallery1_Web1.jpg" server="ftp.benjaminferreiradesigns.com//public_html/" local="3454025309" remote="3166217389752359672" Dst="-1" /><file name="Thumb_Gallery1_Web11.jpg" server="ftp.benjaminferreiradesigns.com//public_html/" local="3454025309" remote="323953104369916664" Dst="-1" /><file name="Thumb_Gallery1_Web13.jpg" server="ftp.benjaminferreiradesigns.com//public_html/" local="3454025309" remote="3210251387335777016" Dst="-1" /><file name="Thumb_Gallery1_Web14.jpg" server="ftp.benjaminferreiradesigns.com//public_html/" local="3454025309" remote="323953104369916664" Dst="-1" /><file name="Thumb_Gallery1_Web12.jpg" server="ftp.benjaminferreiradesigns.com//public_html/" local="3454025309" remote="3166217389752359672" Dst="-1" /><file name="Thumb_Gallery1_Web2.jpg" server="ftp.benjaminferreiradesigns.com//public_html/" local="3454025309" remote="3166217389752359672" Dst="-1" /><file name="Thumb_Gallery1_Web3.jpg" server="ftp.benjaminferreiradesigns.com//public_html/" local="3454025309" remote="3166217389752359672" Dst="-1" /><file name="Thumb_Gallery1_Web4.jpg" server="ftp.benjaminferreiradesigns.com//public_html/" local="3454025310" remote="3052214045590067960" Dst="-1" /><file name="Thumb_Gallery1_Web5.jpg" server="ftp.benjaminferreiradesigns.com//public_html/" local="3454025310" remote="3052214045590067960" Dst="-1" /><file name="Thumb_Gallery1_Web6.jpg" server="ftp.benjaminferreiradesigns.com//public_html/" local="3454025310" remote="3189603589758294776" Dst="-1" /><file name="Thumb_Gallery1_Web7.jpg" server="ftp.benjaminferreiradesigns.com//public_html/" local="3454025310" remote="3166217389752359672" Dst="-1" /><file name="Thumb_Gallery1_Web8.jpg" server="ftp.benjaminferreiradesigns.com//public_html/" local="3454025310" remote="3166217389752359672" Dst="-1" /><file name="Thumb_Gallery1_Web9.jpg" server="ftp.benjaminferreiradesigns.com//public_html/" local="3454025310" remote="323953104369916664" Dst="-1" /><file name="Thumb_Gallery2_Book2.jpg" server="ftp.benjaminferreiradesigns.com//public_html/" local="3454025311" remote="3049023675163122424" Dst="-1" /><file name="Thumb_Gallery3_Book3.jpg" server="ftp.benjaminferreiradesigns.com//public_html/" local="3454025311" remote="3219616340186405624" Dst="-1" /><file name="Thumb_Gallery4_Book4.jpg" server="ftp.benjaminferreiradesigns.com//public_html/" local="3454025311" remote="3189551706553359096" Dst="-1" /><file name="Thumb_Gallery5_Book5.jpg" server="ftp.benjaminferreiradesigns.com//public_html/" local="3454025311" remote="323953104369916664" Dst="-1" /><file name="Thumb_Gallery6_Book6.jpg" server="ftp.benjaminferreiradesigns.com//public_html/" local="3454025311" remote="3189583454951611128" Dst="-1" /><file name="Thumb_Gallery7_Book7.jpg" server="ftp.benjaminferreiradesigns.com//public_html/" local="3454025311" remote="3189551156797545208" Dst="-1" /><file name="Thumb_Gallery8_Book8.png" server="ftp.benjaminferreiradesigns.com//public_html/" local="3454025311" remote="1667473914564614904" Dst="-1" /><file name="Thumb_Gallery9_Book9.png" server="ftp.benjaminferreiradesigns.com//public_html/" local="3454025311" remote="2053851715133414136" Dst="-1" /></dwsync>